G1B1_distributions-0.2.dist-info/DESCRIPTION.rst
G1B1_distributions-0.2.dist-info/METADATA
G1B1_distributions-0.2.dist-info/RECORD
G1B1_distributions-0.2.dist-info/WHEEL
G1B1_distributions-0.2.dist-info/metadata.json
G1B1_distributions-0.2.dist-info/top_level.txt
GB_distributions/Binomialdistribution.py
GB_distributions/Gaussiandistribution.py
GB_distributions/Generaldistribution.py
GB_distributions/__init__.py
