Metadata-Version: 2.0
Name: G1B1-distributions
Version: 0.2
Summary: Gaussian distributions and Binomial distribution
Home-page: UNKNOWN
Author: UNKNOWN
Author-email: UNKNOWN
License: UNKNOWN
Platform: UNKNOWN
